mrcsmooth/__init__.py
mrcsmooth/__main__.py
mrcsmooth/arguments.py
mrcsmooth/runner.py
mrcsmooth-0.2.dist-info/COPYING
mrcsmooth-0.2.dist-info/LICENSE
mrcsmooth-0.2.dist-info/METADATA
mrcsmooth-0.2.dist-info/WHEEL
mrcsmooth-0.2.dist-info/entry_points.txt
mrcsmooth-0.2.dist-info/top_level.txt
mrcsmooth-0.2.dist-info/RECORD
